pydevtips/__init__.py
pydevtips/fftconvolve.py
pydevtips/utils.py
pydevtips-0.0.4.dist-info/LICENSE
pydevtips-0.0.4.dist-info/METADATA
pydevtips-0.0.4.dist-info/WHEEL
pydevtips-0.0.4.dist-info/RECORD
