Metadata-Version: 2.1
Name: pydevtips
Version: 0.0.4
Summary: Functions and scripts to demonstrate Python development tips.
License: MIT
Author: Eric Bezzam
Author-email: ebezzam@gmail.com
Requires-Python: >=3.10,<4.0
Classifier: License :: OSI Approved :: MIT License
Classifier: Programming Language :: Python :: 3
Classifier: Programming Language :: Python :: 3.10
Classifier: Programming Language :: Python :: 3.11
Classifier: Programming Language :: Python :: 3.12
Classifier: Programming Language :: Python :: 3.13
Requires-Dist: hydra-core (>=1.3.2,<2.0.0)
Requires-Dist: matplotlib (>=3.9.2,<4.0.0)
Requires-Dist: numpy (>=2.1.2,<3.0.0)
Requires-Dist: scipy (>=1.14.1,<2.0.0)
Requires-Dist: tqdm (>=4.66.5,<5.0.0)
